llama_index/embeddings/llamafile/__init__.py
llama_index/embeddings/llamafile/base.py
llama_index_embeddings_llamafile-0.4.1.dist-info/METADATA
llama_index_embeddings_llamafile-0.4.1.dist-info/WHEEL
llama_index_embeddings_llamafile-0.4.1.dist-info/licenses/LICENSE
llama_index_embeddings_llamafile-0.4.1.dist-info/RECORD
